eia_client/__init__.py
eia_client/api_key.py
eia_client/cli.py
eia_client/client.py
eia_client/parse.py
eia_client/utils.py
eia_client/endpoint/__init__.py
eia_client/endpoint/builder.py
eia_client/endpoint/electricity_retail_sales.py
eia_client/endpoint/total_energy.py
eia_client-0.4.1.dist-info/LICENSE
eia_client-0.4.1.dist-info/METADATA
eia_client-0.4.1.dist-info/WHEEL
eia_client-0.4.1.dist-info/top_level.txt
eia_client-0.4.1.dist-info/RECORD
