Metadata-Version: 2.1
Name: eia-client
Version: 0.4.1
Summary: EIA Open Data API Python Client
Home-page: https://github.com/tayeva/eia-client-python
Author: tayeva
Author-email: 124453543+tayeva@users.noreply.github.com
Classifier: Development Status :: 1 - Planning
Classifier: Intended Audience :: Science/Research
Classifier: Programming Language :: Python :: 3
Classifier: License :: OSI Approved :: Apache Software License
Classifier: Operating System :: OS Independent
Requires-Python: >=3.7
License-File: LICENSE
Requires-Dist: numpy
Requires-Dist: pandas
Requires-Dist: pyarrow
Requires-Dist: requests
Provides-Extra: dev
Requires-Dist: autopep8 ; extra == 'dev'
Requires-Dist: black ; extra == 'dev'
Requires-Dist: build ; extra == 'dev'
Requires-Dist: flake8 ; extra == 'dev'
Requires-Dist: furo ; extra == 'dev'
Requires-Dist: mccabe ; extra == 'dev'
Requires-Dist: pycodestyle ; extra == 'dev'
Requires-Dist: pyflakes ; extra == 'dev'
Requires-Dist: pylint ; extra == 'dev'
Requires-Dist: pytest ; extra == 'dev'
Requires-Dist: sphinx ; extra == 'dev'
Requires-Dist: twine ; extra == 'dev'
Requires-Dist: yapf ; extra == 'dev'
Provides-Extra: notebook
Requires-Dist: jupyter ; extra == 'notebook'
Requires-Dist: matplotlib ; extra == 'notebook'
